MITgcmutils/__init__.py
MITgcmutils/conversion.py
MITgcmutils/density.py
MITgcmutils/diagnostics.py
MITgcmutils/mds.py
MITgcmutils/mnc.py
MITgcmutils/netcdf.py
MITgcmutils/ptracers.py
MITgcmutils/utils.py
MITgcmutils/cs/__init__.py
MITgcmutils/cs/pcol.py
MITgcmutils/examples/__init__.py
MITgcmutils/examples/eg_utils.py
MITgcmutils/llc/__init__.py
MITgcmutils/llc/llc.py
MITgcmutils-0.2.1.data/scripts/gluemncbig
MITgcmutils-0.2.1.dist-info/LICENSE.txt
MITgcmutils-0.2.1.dist-info/METADATA
MITgcmutils-0.2.1.dist-info/WHEEL
MITgcmutils-0.2.1.dist-info/top_level.txt
MITgcmutils-0.2.1.dist-info/RECORD
