Metadata-Version: 2.1
Name: MITgcmutils
Version: 0.2.1
Summary: Python utilities for MITgcm
Home-page: http://mitgcm.org/
Author: MITgcm Developers and Contributors
Author-email: mitgcm-support@mitgcm.org
License: UNKNOWN
Platform: UNKNOWN
Classifier: Programming Language :: Python
Classifier: License :: OSI Approved :: MIT License
Classifier: Operating System :: OS Independent
License-File: LICENSE.txt
Requires-Dist: numpy
Requires-Dist: matplotlib
